data_splitter/__init__.py
data_splitter/splitter.py
data_splitter-0.0.4.dist-info/LICENSE
data_splitter-0.0.4.dist-info/METADATA
data_splitter-0.0.4.dist-info/WHEEL
data_splitter-0.0.4.dist-info/entry_points.txt
data_splitter-0.0.4.dist-info/top_level.txt
data_splitter-0.0.4.dist-info/RECORD
