Metadata-Version: 2.1
Name: data-splitter
Version: 0.0.4
Summary: Hash function based data splitter.
Home-page: https://github.com/siulkilulki/data-splitter
Author: Dawid Jurkiewicz
Author-email: dawjur@amu.edu.pl
License: UNKNOWN
Platform: UNKNOWN
Classifier: Programming Language :: Python :: 3
Classifier: Programming Language :: Python :: 3.6
Classifier: Programming Language :: Python :: 3.7
Classifier: License :: OSI Approved :: MIT License
Classifier: Operating System :: OS Independent
Requires-Dist: tqdm
